Metadata-Version: 2.1
Name: flake8-forbid-visual-indent
Version: 0.0.2
Summary: Flake8 plugin that disallows visual indentation
Home-page: https://github.com/ateraz/flake8-forbid-visual-indent
Maintainer: Andrii Teraz
Maintainer-email: andrey.teraz@gmail.com
License: UNKNOWN
Platform: UNKNOWN
Classifier: Programming Language :: Python
Classifier: Programming Language :: Python :: 3
Classifier: Programming Language :: Python :: 3.7
Classifier: Programming Language :: Python :: 3.8
Classifier: Programming Language :: Python :: Implementation :: CPython
Requires-Python: >=3.7.0
License-File: LICENSE
